country_registry/__init__.py
country_registry/data/countries/AD.json
country_registry/data/countries/AE.json
country_registry/data/countries/AF.json
country_registry/data/countries/AG.json
country_registry/data/countries/AI.json
country_registry/data/countries/AL.json
country_registry/data/countries/AM.json
country_registry/data/countries/AO.json
country_registry/data/countries/AQ.json
country_registry/data/countries/AR.json
country_registry/data/countries/AS.json
country_registry/data/countries/AT.json
country_registry/data/countries/AU.json
country_registry/data/countries/AW.json
country_registry/data/countries/AX.json
country_registry/data/countries/AZ.json
country_registry/data/countries/BA.json
country_registry/data/countries/BB.json
country_registry/data/countries/BD.json
country_registry/data/countries/BE.json
country_registry/data/countries/BF.json
country_registry/data/countries/BG.json
country_registry/data/countries/BH.json
country_registry/data/countries/BI.json
country_registry/data/countries/BJ.json
country_registry/data/countries/BL.json
country_registry/data/countries/BM.json
country_registry/data/countries/BN.json
country_registry/data/countries/BO.json
country_registry/data/countries/BQ.json
country_registry/data/countries/BR.json
country_registry/data/countries/BS.json
country_registry/data/countries/BT.json
country_registry/data/countries/BV.json
country_registry/data/countries/BW.json
country_registry/data/countries/BY.json
country_registry/data/countries/BZ.json
country_registry/data/countries/CA.json
country_registry/data/countries/CC.json
country_registry/data/countries/CD.json
country_registry/data/countries/CF.json
country_registry/data/countries/CG.json
country_registry/data/countries/CH.json
country_registry/data/countries/CI.json
country_registry/data/countries/CK.json
country_registry/data/countries/CL.json
country_registry/data/countries/CM.json
country_registry/data/countries/CN.json
country_registry/data/countries/CO.json
country_registry-0.1.2.dist-info/LICENSE
country_registry-0.1.2.dist-info/METADATA
country_registry-0.1.2.dist-info/WHEEL
country_registry-0.1.2.dist-info/RECORD
