Metadata-Version: 2.1
Name: country_registry
Version: 0.1.2
Summary: Return useful information for every country in the ISO 3166 standard.
Author: Avishay Maor
Author-email: avishaym@cashcow.com
Requires-Python: >=3.12,<4.0
Classifier: Programming Language :: Python :: 3
Classifier: Programming Language :: Python :: 3.12
Classifier: Programming Language :: Python :: 3.13
Requires-Dist: loguru (>=0.7.3,<0.8.0)
Requires-Dist: pydantic (>=2.10.5,<3.0.0)
Requires-Dist: toml (>=0.10.2,<0.11.0)
